{
            "timestamp": "2025-05-11 16:20:24",
            "cpu": "11.0",
            "memory": {
                "percent": "4.00",
                "used": "866.26",
                "total": "18432"
            },
            "disk": "3%",
            "network": {"en4":{"rx":"0 bytes","tx":"0 bytes"},"en5":{"rx":"0 bytes","tx":"0 bytes"},"en6":{"rx":"0 bytes","tx":"0 bytes"},"bridge0":{"rx":"0 bytes","tx":"0 bytes"},"en0":{"rx":"441 bytes","tx":"2360841904 bytes"},"en1":{"rx":"0 bytes","tx":"0 bytes"},"en2":{"rx":"0 bytes","tx":"0 bytes"},"en3":{"rx":"0 bytes","tx":"0 bytes"}},
            "uptime": "9 days,  1:13, 2 users, load averages: 1.61 2.06 2.28",
            "intrusions": "       0"
        }
